hostfm/__init__.py
hostfm/errors.py
hostfm/hosts.py
hostfm/type.py
hostfm/utils.py
python_hostfm-0.1.1.dist-info/LICENSE
python_hostfm-0.1.1.dist-info/METADATA
python_hostfm-0.1.1.dist-info/WHEEL
python_hostfm-0.1.1.dist-info/top_level.txt
python_hostfm-0.1.1.dist-info/RECORD
